<?xml version="1.0" encoding="utf-8"?>
<publishData>
  <publishProfile publishUrl="C:\Users\WALI\Desktop\Publish App\IMSAPI\IMSAPI-20160803" deleteExistingFiles="True" ftpAnonymousLogin="False" ftpPassiveMode="True" msdeploySite="" msdeploySiteID="" msdeployRemoteSitePhysicalPath="" msdeployAllowUntrustedCertificate="False" msdeploySkipExtraFilesOnServer="True" msdeployMarkAsApp="False" profileName="Profile1" publishMethod="FileSystem" replaceMatchingFiles="False" userName="" savePWD="False" userPWD="" SelectedForPublish="True">
    <file relUrl="Scripts/jquery-1.7.1.js" publishTime="06/09/2016 02:57:32" />
    <file relUrl="Content/themes/base/minified/jquery.ui.slider.min.css" publishTime="06/09/2016 02:57:36" />
    <file relUrl="bin/Antlr3.Runtime.dll" publishTime="06/09/2016 02:57:44" />
    <file relUrl="bin/System.Web.Providers.dll" publishTime="06/09/2016 02:57:44" />
    <file relUrl="Content/themes/base/jquery.ui.datepicker.css" publishTime="06/09/2016 02:57:36" />
    <file relUrl="bin/System.Web.Helpers.xml" publishTime="06/09/2016 02:57:38" />
    <file relUrl="bin/IMSAPI.pdb" publishTime="08/03/2016 18:15:07" />
    <file relUrl="Content/themes/base/minified/jquery-ui.min.css" publishTime="06/09/2016 02:57:34" />
    <file relUrl="Scripts/jquery.unobtrusive-ajax.js" publishTime="06/09/2016 02:57:36" />
    <file relUrl="Content/themes/base/minified/jquery.ui.autocomplete.min.css" publishTime="06/09/2016 02:57:36" />
    <file relUrl="bin/Class/SubmitInvoices.cs" publishTime="08/03/2016 18:04:35" />
    <file relUrl="bin/Microsoft.Web.Infrastructure.dll" publishTime="06/09/2016 02:57:38" />
    <file relUrl="Content/themes/base/images/ui-bg_highlight-soft_75_cccccc_1x100.png" publishTime="06/09/2016 02:57:36" />
    <file relUrl="bin/System.Web.WebPages.dll" publishTime="06/09/2016 02:57:38" />
    <file relUrl="bin/Microsoft.Practices.Unity.dll" publishTime="01/09/2014 22:33:06" />
    <file relUrl="Views/Web.config" publishTime="06/09/2016 02:57:10" />
    <file relUrl="Content/themes/base/jquery.ui.selectable.css" publishTime="06/09/2016 02:57:36" />
    <file relUrl="Content/themes/base/minified/images/ui-icons_222222_256x240.png" publishTime="06/09/2016 02:57:36" />
    <file relUrl="Scripts/jquery.validate.js" publishTime="06/09/2016 02:57:34" />
    <file relUrl="bin/System.Web.Razor.xml" publishTime="06/09/2016 02:57:38" />
    <file relUrl="bin/ICSharpCode.SharpZipLib.dll" publishTime="06/23/2016 19:24:37" />
    <file relUrl="bin/Class/MultipleInvoice.cs" publishTime="06/11/2016 03:12:08" />
    <file relUrl="Content/themes/base/jquery.ui.all.css" publishTime="06/09/2016 02:57:36" />
    <file relUrl="bin/System.Web.Razor.dll" publishTime="06/09/2016 02:57:38" />
    <file relUrl="Views/Home/Index.cshtml" publishTime="06/09/2016 02:57:10" />
    <file relUrl="bin/System.Net.Http.Formatting.xml" publishTime="06/09/2016 02:57:40" />
    <file relUrl="Scripts/jquery.validate.unobtrusive.min.js" publishTime="06/09/2016 02:57:36" />
    <file relUrl="bin/GitSharp.dll" publishTime="06/23/2016 19:24:38" />
    <file relUrl="Views/Shared/Error.cshtml" publishTime="06/09/2016 02:57:10" />
    <file relUrl="Content/themes/base/minified/jquery.ui.progressbar.min.css" publishTime="06/09/2016 02:57:36" />
    <file relUrl="Scripts/jquery-1.7.1.min.js" publishTime="06/09/2016 02:57:32" />
    <file relUrl="Images/orderedList4.png" publishTime="06/09/2016 02:57:10" />
    <file relUrl="Content/themes/base/images/ui-bg_glass_55_fbf9ee_1x400.png" publishTime="06/09/2016 02:57:36" />
    <file relUrl="Content/themes/base/minified/jquery.ui.accordion.min.css" publishTime="06/09/2016 02:57:36" />
    <file relUrl="Content/themes/base/jquery-ui.css" publishTime="06/09/2016 02:57:36" />
    <file relUrl="Content/themes/base/jquery.ui.resizable.css" publishTime="06/09/2016 02:57:36" />
    <file relUrl="Images/accent.png" publishTime="06/09/2016 02:57:10" />
    <file relUrl="bin/System.Net.Http.Formatting.dll" publishTime="06/09/2016 02:57:40" />
    <file relUrl="Content/themes/base/jquery.ui.tabs.css" publishTime="06/09/2016 02:57:36" />
    <file relUrl="bin/System.Web.WebPages.xml" publishTime="06/09/2016 02:57:40" />
    <file relUrl="Scripts/knockout-2.1.0.debug.js" publishTime="06/09/2016 02:57:44" />
    <file relUrl="Images/orderedList1.png" publishTime="06/09/2016 02:57:10" />
    <file relUrl="Content/themes/base/images/ui-icons_2e83ff_256x240.png" publishTime="06/09/2016 02:57:36" />
    <file relUrl="Content/themes/base/minified/jquery.ui.tabs.min.css" publishTime="06/09/2016 02:57:36" />
    <file relUrl="bin/IMSDAL.pdb" publishTime="08/03/2016 18:15:04" />
    <file relUrl="bin/System.Web.WebPages.Deployment.dll" publishTime="06/09/2016 02:57:38" />
    <file relUrl="bin/Newtonsoft.Json.dll" publishTime="06/09/2016 02:57:38" />
    <file relUrl="Scripts/jquery-ui-1.8.20.min.js" publishTime="06/09/2016 02:57:34" />
    <file relUrl="Images/heroAccent.png" publishTime="06/09/2016 02:57:10" />
    <file relUrl="Global.asax" publishTime="06/09/2016 02:57:10" />
    <file relUrl="bin/EntityFramework.xml" publishTime="06/20/2016 14:02:37" />
    <file relUrl="bin/Microsoft.Practices.ObjectBuilder2.dll" publishTime="01/09/2014 22:33:04" />
    <file relUrl="Images/orderedList3.png" publishTime="06/09/2016 02:57:10" />
    <file relUrl="bin/Microsoft.Practices.EnterpriseLibrary.Data.dll" publishTime="01/09/2014 22:32:58" />
    <file relUrl="Images/orderedList5.png" publishTime="06/09/2016 02:57:10" />
    <file relUrl="Content/themes/base/minified/jquery.ui.theme.min.css" publishTime="06/09/2016 02:57:36" />
    <file relUrl="Web.config" publishTime="08/03/2016 18:16:04" />
    <file relUrl="Images/orderedList8.png" publishTime="06/09/2016 02:57:10" />
    <file relUrl="bin/Class/InvoiceHeader.cs" publishTime="06/21/2016 12:56:02" />
    <file relUrl="bin/EntityFramework.SqlServer.dll" publishTime="06/20/2016 14:02:37" />
    <file relUrl="Content/themes/base/minified/images/ui-bg_glass_65_ffffff_1x400.png" publishTime="06/09/2016 02:57:36" />
    <file relUrl="packages.config" publishTime="06/23/2016 19:24:42" />
    <file relUrl="Content/themes/base/jquery.ui.dialog.css" publishTime="06/09/2016 02:57:36" />
    <file relUrl="bin/System.Net.Http.xml" publishTime="06/09/2016 02:57:42" />
    <file relUrl="bin/Newtonsoft.Json.xml" publishTime="06/09/2016 02:57:38" />
    <file relUrl="Content/themes/base/minified/images/ui-icons_2e83ff_256x240.png" publishTime="06/09/2016 02:57:36" />
    <file relUrl="Content/themes/base/minified/images/ui-bg_glass_55_fbf9ee_1x400.png" publishTime="06/09/2016 02:57:36" />
    <file relUrl="Content/themes/base/images/ui-icons_222222_256x240.png" publishTime="06/09/2016 02:57:36" />
    <file relUrl="bin/Class/Token.cs" publishTime="07/25/2016 15:40:06" />
    <file relUrl="Content/themes/base/minified/images/ui-icons_cd0a0a_256x240.png" publishTime="06/09/2016 02:57:36" />
    <file relUrl="bin/Class/InvoiceDetails.cs" publishTime="06/10/2016 01:29:46" />
    <file relUrl="bin/System.Web.Optimization.dll" publishTime="06/09/2016 02:57:44" />
    <file relUrl="Content/themes/base/minified/jquery.ui.dialog.min.css" publishTime="06/09/2016 02:57:36" />
    <file relUrl="bin/IMSBLL.dll" publishTime="08/03/2016 18:15:05" />
    <file relUrl="bin/System.Web.Mvc.xml" publishTime="06/09/2016 02:57:40" />
    <file relUrl="Views/ims/token.cshtml" publishTime="06/09/2016 05:16:04" />
    <file relUrl="Content/themes/base/minified/images/ui-bg_glass_75_e6e6e6_1x400.png" publishTime="06/09/2016 02:57:36" />
    <file relUrl="Views/_ViewStart.cshtml" publishTime="06/09/2016 02:57:10" />
    <file relUrl="bin/Controllers/tokenController.cs" publishTime="06/28/2016 15:34:06" />
    <file relUrl="Content/themes/base/jquery.ui.autocomplete.css" publishTime="06/09/2016 02:57:36" />
    <file relUrl="bin/EntityFramework.SqlServer.xml" publishTime="06/20/2016 14:02:37" />
    <file relUrl="bin/Controllers/HomeController.cs" publishTime="06/20/2016 12:59:19" />
    <file relUrl="Content/themes/base/images/ui-bg_glass_75_e6e6e6_1x400.png" publishTime="06/09/2016 02:57:36" />
    <file relUrl="favicon.ico" publishTime="06/09/2016 02:57:10" />
    <file relUrl="bin/IMSAPI.dll" publishTime="08/03/2016 18:15:07" />
    <file relUrl="Scripts/jquery.validate-vsdoc.js" publishTime="06/09/2016 02:57:34" />
    <file relUrl="Content/themes/base/jquery.ui.theme.css" publishTime="06/09/2016 02:57:36" />
    <file relUrl="Content/themes/base/minified/images/ui-icons_454545_256x240.png" publishTime="06/09/2016 02:57:36" />
    <file relUrl="Content/themes/base/images/ui-bg_glass_95_fef1ec_1x400.png" publishTime="06/09/2016 02:57:36" />
    <file relUrl="Content/themes/base/minified/images/ui-bg_glass_75_dadada_1x400.png" publishTime="06/09/2016 02:57:36" />
    <file relUrl="Content/themes/base/minified/images/ui-bg_flat_75_ffffff_40x100.png" publishTime="06/09/2016 02:57:36" />
    <file relUrl="Models/Token.ascx" publishTime="06/09/2016 03:35:06" />
    <file relUrl="Images/orderedList7.png" publishTime="06/09/2016 02:57:10" />
    <file relUrl="Scripts/jquery-1.7.1-vsdoc.js" publishTime="06/09/2016 02:57:32" />
    <file relUrl="bin/System.Net.Http.WebRequest.xml" publishTime="06/09/2016 02:57:42" />
    <file relUrl="Content/themes/base/images/ui-bg_glass_75_dadada_1x400.png" publishTime="06/09/2016 02:57:36" />
    <file relUrl="Content/themes/base/images/ui-icons_454545_256x240.png" publishTime="06/09/2016 02:57:36" />
    <file relUrl="Content/themes/base/jquery.ui.button.css" publishTime="06/09/2016 02:57:36" />
    <file relUrl="bin/IMSBLL.pdb" publishTime="08/03/2016 18:15:05" />
    <file relUrl="Content/themes/base/jquery.ui.core.css" publishTime="06/09/2016 02:57:36" />
    <file relUrl="Content/themes/base/minified/images/ui-icons_888888_256x240.png" publishTime="06/09/2016 02:57:36" />
    <file relUrl="Content/themes/base/images/ui-bg_glass_65_ffffff_1x400.png" publishTime="06/09/2016 02:57:36" />
    <file relUrl="Content/themes/base/minified/images/ui-bg_glass_95_fef1ec_1x400.png" publishTime="06/09/2016 02:57:36" />
    <file relUrl="bin/System.Web.WebPages.Razor.xml" publishTime="06/09/2016 02:57:38" />
    <file relUrl="Views/Shared/_Layout.cshtml" publishTime="06/20/2016 14:05:51" />
    <file relUrl="Images/orderedList2.png" publishTime="06/09/2016 02:57:10" />
    <file relUrl="Content/themes/base/images/ui-icons_cd0a0a_256x240.png" publishTime="06/09/2016 02:57:36" />
    <file relUrl="bin/WebGrease.dll" publishTime="06/09/2016 02:57:44" />
    <file relUrl="bin/Controllers/SingleInvoiceController.cs" publishTime="08/03/2016 14:44:19" />
    <file relUrl="Images/orderedList9.png" publishTime="06/09/2016 02:57:10" />
    <file relUrl="Content/themes/base/jquery.ui.accordion.css" publishTime="06/09/2016 02:57:36" />
    <file relUrl="bin/System.Web.Http.WebHost.dll" publishTime="06/09/2016 02:57:42" />
    <file relUrl="bin/Controllers/MultipleInvoiceController.cs" publishTime="07/01/2016 15:27:08" />
    <file relUrl="Content/themes/base/images/ui-bg_flat_0_aaaaaa_40x100.png" publishTime="06/09/2016 02:57:36" />
    <file relUrl="Content/themes/base/jquery.ui.slider.css" publishTime="06/09/2016 02:57:36" />
    <file relUrl="Content/themes/base/minified/jquery.ui.resizable.min.css" publishTime="06/09/2016 02:57:36" />
    <file relUrl="Content/themes/base/minified/jquery.ui.core.min.css" publishTime="06/09/2016 02:57:36" />
    <file relUrl="Content/themes/base/images/ui-bg_flat_75_ffffff_40x100.png" publishTime="06/09/2016 02:57:36" />
    <file relUrl="bin/Microsoft.Practices.EnterpriseLibrary.Common.dll" publishTime="01/09/2014 22:33:02" />
    <file relUrl="Content/Site.css" publishTime="06/09/2016 02:57:10" />
    <file relUrl="Scripts/jquery.validate.unobtrusive.js" publishTime="06/09/2016 02:57:36" />
    <file relUrl="bin/Winterdom.IO.FileMap.dll" publishTime="06/23/2016 19:24:38" />
    <file relUrl="bin/System.Web.WebPages.Razor.dll" publishTime="06/09/2016 02:57:38" />
    <file relUrl="bin/Class/GenericCollection.cs" publishTime="06/21/2016 16:01:56" />
    <file relUrl="bin/System.Web.Mvc.dll" publishTime="06/09/2016 02:57:40" />
    <file relUrl="bin/EntityFramework.dll" publishTime="06/20/2016 14:02:37" />
    <file relUrl="bin/Tamir.SharpSSH.dll" publishTime="06/23/2016 19:24:37" />
    <file relUrl="bin/System.Web.Http.WebHost.xml" publishTime="06/09/2016 02:57:42" />
    <file relUrl="Scripts/jquery-ui-1.8.20.js" publishTime="06/09/2016 02:57:34" />
    <file relUrl="bin/System.Web.Http.dll" publishTime="06/09/2016 02:57:42" />
    <file relUrl="Scripts/modernizr-2.5.3.js" publishTime="06/09/2016 02:57:36" />
    <file relUrl="bin/System.Web.Http.xml" publishTime="06/09/2016 02:57:42" />
    <file relUrl="Content/themes/base/images/ui-icons_888888_256x240.png" publishTime="06/09/2016 02:57:36" />
    <file relUrl="Content/themes/base/jquery.ui.progressbar.css" publishTime="06/09/2016 02:57:36" />
    <file relUrl="Images/bullet.png" publishTime="06/09/2016 02:57:10" />
    <file relUrl="Content/themes/base/minified/jquery.ui.selectable.min.css" publishTime="06/09/2016 02:57:36" />
    <file relUrl="Scripts/knockout-2.1.0.js" publishTime="06/09/2016 02:57:44" />
    <file relUrl="bin/System.Net.Http.WebRequest.dll" publishTime="06/09/2016 02:57:42" />
    <file relUrl="Images/orderedList6.png" publishTime="06/09/2016 02:57:10" />
    <file relUrl="bin/System.Web.Helpers.dll" publishTime="06/09/2016 02:57:38" />
    <file relUrl="Scripts/_references.js" publishTime="06/09/2016 02:57:10" />
    <file relUrl="Content/themes/base/minified/images/ui-bg_flat_0_aaaaaa_40x100.png" publishTime="06/09/2016 02:57:36" />
    <file relUrl="Scripts/jquery.validate.min.js" publishTime="06/09/2016 02:57:34" />
    <file relUrl="bin/GitSharp.Core.dll" publishTime="06/23/2016 19:24:38" />
    <file relUrl="bin/IMSDAL.dll" publishTime="08/03/2016 18:15:04" />
    <file relUrl="Content/themes/base/minified/jquery.ui.button.min.css" publishTime="06/09/2016 02:57:36" />
    <file relUrl="Scripts/jquery.unobtrusive-ajax.min.js" publishTime="06/09/2016 02:57:36" />
    <file relUrl="bin/Class/GlobalCode.cs" publishTime="07/01/2016 15:27:08" />
    <file relUrl="Content/themes/base/jquery.ui.base.css" publishTime="06/09/2016 02:57:36" />
    <file relUrl="Content/themes/base/minified/jquery.ui.datepicker.min.css" publishTime="06/09/2016 02:57:36" />
    <file relUrl="bin/System.Net.Http.dll" publishTime="06/09/2016 02:57:42" />
    <file relUrl="Images/orderedList0.png" publishTime="06/09/2016 02:57:10" />
    <file relUrl="Content/themes/base/minified/images/ui-bg_highlight-soft_75_cccccc_1x100.png" publishTime="06/09/2016 02:57:36" />
    <file relUrl="bin/System.Web.WebPages.Deployment.xml" publishTime="06/09/2016 02:57:38" />
  </publishProfile>
</publishData>